pack_hello/__init__.py
pack_hello/file2_name.py
pack_hello/hello.py
pack_hello-0.0.1.dist-info/METADATA
pack_hello-0.0.1.dist-info/WHEEL
pack_hello-0.0.1.dist-info/top_level.txt
pack_hello-0.0.1.dist-info/RECORD
