Metadata-Version: 2.1
Name: pack_hello
Version: 0.0.1
Summary: Pacote de saudação
Home-page: https://github.com/Car-Lopes/projeto_package
Author: Carlos_Lopes
Author-email: car.l1991@yahoo.com.br
Requires-Python: >=3.0
